rpi5_ws2812/__init__.py
rpi5_ws2812/ws2812.py
rpi5_ws2812-0.1.1.dist-info/LICENSE
rpi5_ws2812-0.1.1.dist-info/METADATA
rpi5_ws2812-0.1.1.dist-info/WHEEL
rpi5_ws2812-0.1.1.dist-info/top_level.txt
rpi5_ws2812-0.1.1.dist-info/RECORD
