Metadata-Version: 2.1
Name: rpi5-ws2812
Version: 0.1.1
Summary: A library to control WS2812 LEDs with a Raspberry Pi 5
Home-page: https://github.com/niklasr22/rpi5-ws2812
Author-email: byrousset@gmail.com
License: MIT
Project-URL: Bug Tracker, https://github.com/niklasr22/rpi5-ws2812/issues
Keywords: raspberry,pi,rpi,ws2812,led,spi
Classifier: Programming Language :: Python :: 3
Classifier: License :: OSI Approved :: MIT License
Classifier: Operating System :: OS Independent
Requires-Python: >=3.11
License-File: LICENSE
Requires-Dist: spidev
Requires-Dist: numpy
